basecampy3/__init__.py
basecampy3/__version__.py
basecampy3/bc3_api.py
basecampy3/bc3_cli.py
basecampy3/config.py
basecampy3/constants.py
basecampy3/exc.py
basecampy3/log.py
basecampy3/oauth_server.py
basecampy3/rated_semaphore.py
basecampy3/token_requestor.py
basecampy3/transport_adapter.py
basecampy3/cache/__init__.py
basecampy3/cache/dictionary_cache.py
basecampy3/cache/response_cache.py
basecampy3/endpoints/__init__.py
basecampy3/endpoints/_base.py
basecampy3/endpoints/answers.py
basecampy3/endpoints/campfire_lines.py
basecampy3/endpoints/campfires.py
basecampy3/endpoints/comments.py
basecampy3/endpoints/message_boards.py
basecampy3/endpoints/message_categories.py
basecampy3/endpoints/messages.py
basecampy3/endpoints/people.py
basecampy3/endpoints/project_constructions.py
basecampy3/endpoints/projects.py
basecampy3/endpoints/recordings.py
basecampy3/endpoints/templates.py
basecampy3/endpoints/todolist_groups.py
basecampy3/endpoints/todolists.py
basecampy3/endpoints/todos.py
basecampy3/endpoints/todosets.py
basecampy3/endpoints/util.py
basecampy3/urls/__init__.py
basecampy3/urls/basecamp.py
basecampy3/urls/url.py
basecampy3/urls/util.py
basecampy3/urls/endpoints/__init__.py
basecampy3/urls/endpoints/attachments.py
basecampy3/urls/endpoints/base.py
basecampy3/urls/endpoints/campfire_lines.py
basecampy3/urls/endpoints/campfires.py
basecampy3/urls/endpoints/chatbots.py
basecampy3/urls/endpoints/client_approvals.py
basecampy3/urls/endpoints/client_correspondences.py
basecampy3/urls/endpoints/client_replies.py
basecampy3/urls/endpoints/comments.py
basecampy3/urls/endpoints/documents.py
basecampy3/urls/endpoints/forwards.py
basecampy3/urls/endpoints/inbox_replies.py
basecampy3/urls/endpoints/inboxes.py
basecampy3/urls/endpoints/message_boards.py
basecampy3/urls/endpoints/message_types.py
basecampy3/urls/endpoints/messages.py
basecampy3/urls/endpoints/people.py
basecampy3/urls/endpoints/projects.py
basecampy3/urls/endpoints/question_answers.py
basecampy3-0.7.2.dist-info/LICENSE
basecampy3-0.7.2.dist-info/METADATA
basecampy3-0.7.2.dist-info/WHEEL
basecampy3-0.7.2.dist-info/entry_points.txt
basecampy3-0.7.2.dist-info/top_level.txt
basecampy3-0.7.2.dist-info/RECORD
