Metadata-Version: 2.1
Name: basecampy3
Version: 0.7.2
Summary: Aims to be the easiest to use version of the Basecamp 3 API
Home-page: https://github.com/phistrom/basecampy3
Author: Phillip Stromberg
Author-email: phillip@strombergs.com
License: MIT
Platform: UNKNOWN
Classifier: Development Status :: 4 - Beta
Classifier: Intended Audience :: Developers
Classifier: Natural Language :: English
Classifier: License :: OSI Approved :: MIT License
Classifier: Programming Language :: Python
Classifier: Programming Language :: Python :: 2
Classifier: Programming Language :: Python :: 2.7
Classifier: Programming Language :: Python :: 3
Requires-Dist: python-dateutil
Requires-Dist: pytz
Requires-Dist: requests
Requires-Dist: six
Requires-Dist: urllib3 (<2.0.0)
Requires-Dist: tzlocal (<=2.1)
